[
  {
    "tagTypeString": "NOA",
    "tagNounAbstractString": "actions",
    "tagNameFullString": "NounAbstract Action",
    "tagNounAbstractSString": "action",
    "tagNameAltString": "NOA_ACT"
  },
  {
    "tagTypeString": "NOA",
    "tagNounAbstractString": "angers",
    "tagNameFullString": "NounAbstract Anger",
    "tagNounAbstractSString": "anger",
    "tagNameAltString": "NOA_ANG"
  },
  {
    "tagTypeString": "NOA",
    "tagNounAbstractString": "corners",
    "tagNameFullString": "NounAbstract Corner",
    "tagNounAbstractSString": "corner",
    "tagNameAltString": "NOA_COR"
  },
  {
    "tagTypeString": "NOA",
    "tagNounAbstractString": "deaths",
    "tagNameFullString": "NounAbstract Death",
    "tagNounAbstractSString": "death",
    "tagNameAltString": "NOA_DEA"
  },
  {
    "tagTypeString": "NOA",
    "tagNounAbstractString": "desolations",
    "tagNameFullString": "NounAbstract Desolation",
    "tagNounAbstractSString": "desolation",
    "tagNameAltString": "NOA_DES"
  },
  {
    "tagTypeString": "NOA",
    "tagNounAbstractString": "exhaustions",
    "tagNameFullString": "NounAbstract Exhaustion",
    "tagNounAbstractSString": "exhaustion",
    "tagNameAltString": "NOA_EXH"
  },
  {
    "tagTypeString": "NOA",
    "tagNounAbstractString": "faiths",
    "tagNameFullString": "NounAbstract Faith",
    "tagNounAbstractSString": "faith",
    "tagNameAltString": "NOA_FAI"
  },
  {
    "tagTypeString": "NOA",
    "tagNounAbstractString": "lifes",
    "tagNameFullString": "NounAbstract Life",
    "tagNounAbstractSString": "life",
    "tagNameAltString": "NOA_LIF"
  },
  {
    "tagTypeString": "NOA",
    "tagNounAbstractString": "loves",
    "tagNameFullString": "NounAbstract Love",
    "tagNounAbstractSString": "love",
    "tagNameAltString": "NOA_LOV"
  },
  {
    "tagTypeString": "NOA",
    "tagNounAbstractString": "noises",
    "tagNameFullString": "NounAbstract Noise",
    "tagNounAbstractSString": "noise",
    "tagNameAltString": "NOA_NOI"
  },
  {
    "tagTypeString": "NOA",
    "tagNounAbstractString": "works",
    "tagNameFullString": "NounAbstract Work",
    "tagNounAbstractSString": "work",
    "tagNameAltString": "NOA_WOR"
  }
]