[
  {
    "visitorCurrentInt": 10,
    "tagMuseumNameAltStringList5": "IVR_SLE",
    "tagMuseumNameAltStringList6": "IVR_DRI",
    "tagMuseumNameAltStringList40": "TVR_GRA",
    "tagMuseumNameAltStringList7": "NDJ_BAD",
    "tagMuseumNameAltStringList41": "TVR_TAL",
    "tagMuseumNameAltStringList8": "NDJ_AWF",
    "tagMuseumNameAltStringList1": "ADJ_SOF",
    "tagMuseumNameAltStringList2": "ADV_PER",
    "tagMuseumNameAltStringList3": "ADV_QUI",
    "tagMuseumNameAltStringList4": "IVR_SIT",
    "tagMuseumNameAltStringList9": "NDV_DES",
    "tagMuseumNameAltStringList37": "TVR_BUY",
    "tagMuseumNameAltStringList36": "TVR_HUS",
    "visitorTotalInt": 134,
    "tagMuseumNameAltStringList0": "ADJ_GOD",
    "tagMuseumNameAltStringList39": "TVR_CAL",
    "tagMuseumNameAltStringList38": "TVR_DES",
    "tagMuseumNameAltStringList33": "SUB_IRQ",
    "tagMuseumNameAltStringList32": "SUB_JUC",
    "indexGlobalInt": 0,
    "tagMuseumNameAltStringList35": "SUB_MED",
    "tagMuseumNameAltStringList34": "SUB_WAS",
    "nameFullString": "Room China",
    "nameAltString": "ROM_CHN",
    "parentNameAltString": "FLR_001",
    "tagMuseumNameAltStringList20": "NOU_STA",
    "fullBoolean": true,
    "tagMuseumNameAltStringList19": "NOU_ANK",
    "tagMuseumNameAltStringList18": "NOA_NOI",
    "tagMuseumNameAltStringList11": "NIV_DIE",
    "explanationStringArray3": "Room China Explanation 4",
    "tagMuseumNameAltStringList10": "NDV_SLO",
    "tagMuseumNameAltStringList13": "NTV_ASS",
    "tagMuseumNameAltStringList12": "NIV_DIS",
    "tagMuseumNameAltStringList15": "NOA_FAI",
    "tagMuseumNameAltStringList14": "NOA_ANG",
    "explanationStringArray0": "Room China Explanation 1",
    "tagMuseumNameAltStringList17": "NOA_ACT",
    "explanationStringArray1": "Room China Explanation 2",
    "tagMuseumNameAltStringList16": "NOA_COR",
    "explanationStringArray2": "Room China Explanation 3",
    "tagMuseumNameAltStringList30": "SUB_ROM",
    "tagMuseumNameAltStringList31": "SUB_NAP",
    "typeString": "ROM",
    "tagMuseumNameAltStringList29": "SUB_DIM",
    "tagMuseumNameAltStringList24": "NOU_PLA",
    "tagMuseumNameAltStringList23": "NOU_SID",
    "tagMuseumNameAltStringList22": "NOU_GUN",
    "tagMuseumNameAltStringList21": "NOU_PAP",
    "tagMuseumNameAltStringList28": "SUB_DMI",
    "indexLocalInt": 0,
    "tagMuseumNameAltStringList27": "SUB_MMO",
    "tagMuseumNameAltStringList26": "SUB_FIR",
    "tagMuseumNameAltStringList25": "NOU_RAI"
  },
  {
    "tagMuseumNameAltStringList5": "IVR_JUM",
    "visitorCurrentInt": 4,
    "tagMuseumNameAltStringList6": "IVR_EAT",
    "tagMuseumNameAltStringList7": "NDJ_BAD",
    "tagMuseumNameAltStringList8": "NDV_DES",
    "tagMuseumNameAltStringList1": "ADJ_BAD",
    "tagMuseumNameAltStringList2": "ADV_QUI",
    "tagMuseumNameAltStringList3": "IVR_DRI",
    "tagMuseumNameAltStringList4": "IVR_RUN",
    "tagMuseumNameAltStringList9": "NIV_DIS",
    "tagMuseumNameAltStringList37": "TVR_SHO",
    "tagMuseumNameAltStringList36": "TVR_GET",
    "tagMuseumNameAltStringList0": "ADJ_GOD",
    "visitorTotalInt": 139,
    "tagMuseumNameAltStringList38": "TVR_FIG",
    "tagMuseumNameAltStringList33": "TVR_CAL",
    "tagMuseumNameAltStringList32": "TVR_DES",
    "indexGlobalInt": 1,
    "tagMuseumNameAltStringList35": "TVR_GRA",
    "tagMuseumNameAltStringList34": "TVR_HUS",
    "nameFullString": "Room Iraq",
    "nameAltString": "ROM_IRQ",
    "parentNameAltString": "FLR_001",
    "tagMuseumNameAltStringList20": "NOU_DCR",
    "fullBoolean": false,
    "tagMuseumNameAltStringList19": "NOU_PLA",
    "tagMuseumNameAltStringList18": "NOU_CRO",
    "tagMuseumNameAltStringList11": "NTV_KIL",
    "explanationStringArray3": "Room Iraq Explanation 4",
    "tagMuseumNameAltStringList10": "NTV_ASS",
    "tagMuseumNameAltStringList13": "NOA_WOR",
    "tagMuseumNameAltStringList12": "NOA_DEA",
    "tagMuseumNameAltStringList15": "NOA_ACT",
    "tagMuseumNameAltStringList14": "NOA_NOI",
    "explanationStringArray0": "Room Iraq Explanation 1",
    "tagMuseumNameAltStringList17": "NOU_DOR",
    "explanationStringArray1": "Room Iraq Explanation 2",
    "tagMuseumNameAltStringList16": "NOA_LIF",
    "explanationStringArray2": "Room Iraq Explanation 3",
    "tagMuseumNameAltStringList30": "SUB_BOD",
    "tagMuseumNameAltStringList31": "SUB_JUC",
    "typeString": "ROM",
    "tagMuseumNameAltStringList29": "SUB_IRQ",
    "tagMuseumNameAltStringList24": "SUB_ITA",
    "tagMuseumNameAltStringList23": "SUB_DRA",
    "tagMuseumNameAltStringList22": "NOU_CIG",
    "tagMuseumNameAltStringList21": "NOU_FIG",
    "tagMuseumNameAltStringList28": "SUB_MED",
    "tagMuseumNameAltStringList27": "SUB_MAR",
    "indexLocalInt": 1,
    "tagMuseumNameAltStringList26": "SUB_ROM",
    "tagMuseumNameAltStringList25": "SUB_DIM"
  },
  {
    "tagMuseumNameAltStringList5": "IVR_EAT",
    "visitorCurrentInt": 8,
    "tagMuseumNameAltStringList6": "IVR_SIN",
    "tagMuseumNameAltStringList7": "IVR_DRI",
    "tagMuseumNameAltStringList8": "NDJ_AWF",
    "tagMuseumNameAltStringList1": "ADJ_SOF",
    "tagMuseumNameAltStringList2": "ADV_PER",
    "tagMuseumNameAltStringList3": "IVR_SLE",
    "tagMuseumNameAltStringList4": "IVR_JUM",
    "tagMuseumNameAltStringList9": "NDJ_BAD",
    "tagMuseumNameAltStringList37": "TVR_HUS",
    "tagMuseumNameAltStringList36": "TVR_SHO",
    "visitorTotalInt": 135,
    "tagMuseumNameAltStringList0": "ADJ_BAD",
    "tagMuseumNameAltStringList39": "TVR_CAL",
    "tagMuseumNameAltStringList38": "TVR_GET",
    "tagMuseumNameAltStringList33": "SUB_DMI",
    "tagMuseumNameAltStringList32": "SUB_MED",
    "indexGlobalInt": 2,
    "tagMuseumNameAltStringList35": "TVR_DRI",
    "tagMuseumNameAltStringList34": "TVR_SEL",
    "nameFullString": "Room Rome",
    "nameAltString": "ROM_ROM",
    "parentNameAltString": "FLR_002",
    "tagMuseumNameAltStringList20": "NOU_CIG",
    "fullBoolean": true,
    "tagMuseumNameAltStringList19": "NOU_ANK",
    "tagMuseumNameAltStringList18": "NOU_DOR",
    "tagMuseumNameAltStringList11": "NIV_DIE",
    "explanationStringArray3": "Room Rome Explanation 4",
    "tagMuseumNameAltStringList10": "NDV_DES",
    "tagMuseumNameAltStringList13": "NTV_ASS",
    "tagMuseumNameAltStringList12": "NIV_DIS",
    "tagMuseumNameAltStringList15": "NOA_NOI",
    "tagMuseumNameAltStringList14": "NOA_COR",
    "explanationStringArray0": "Room Rome Explanation 1",
    "tagMuseumNameAltStringList17": "NOU_PAP",
    "explanationStringArray1": "Room Rome Explanation 2",
    "tagMuseumNameAltStringList16": "NOA_DES",
    "explanationStringArray2": "Room Rome Explanation 3",
    "tagMuseumNameAltStringList30": "SUB_DRA",
    "tagMuseumNameAltStringList31": "SUB_BOD",
    "typeString": "ROM",
    "tagMuseumNameAltStringList29": "SUB_RUS",
    "tagMuseumNameAltStringList24": "NOU_HOD",
    "tagMuseumNameAltStringList23": "NOU_FLO",
    "tagMuseumNameAltStringList22": "NOU_STO",
    "tagMuseumNameAltStringList21": "NOU_SID",
    "tagMuseumNameAltStringList28": "SUB_IRQ",
    "tagMuseumNameAltStringList27": "SUB_ASS",
    "indexLocalInt": 0,
    "tagMuseumNameAltStringList26": "SUB_KIL",
    "tagMuseumNameAltStringList25": "NOU_CRO"
  },
  {
    "visitorCurrentInt": 8,
    "tagMuseumNameAltStringList5": "IVR_SIT",
    "tagMuseumNameAltStringList6": "IVR_EAT",
    "tagMuseumNameAltStringList40": "TVR_SEL",
    "tagMuseumNameAltStringList7": "IVR_RUN",
    "tagMuseumNameAltStringList41": "TVR_GET",
    "tagMuseumNameAltStringList8": "NDJ_AWF",
    "tagMuseumNameAltStringList42": "TVR_SHO",
    "tagMuseumNameAltStringList1": "ADJ_SOF",
    "tagMuseumNameAltStringList2": "ADV_PER",
    "tagMuseumNameAltStringList3": "ADV_QUI",
    "tagMuseumNameAltStringList4": "IVR_SIN",
    "tagMuseumNameAltStringList9": "NDJ_BAD",
    "tagMuseumNameAltStringList37": "SUB_FIR",
    "tagMuseumNameAltStringList36": "SUB_RUS",
    "visitorTotalInt": 132,
    "tagMuseumNameAltStringList0": "ADJ_BAD",
    "tagMuseumNameAltStringList39": "TVR_LOV",
    "tagMuseumNameAltStringList38": "TVR_HUS",
    "tagMuseumNameAltStringList33": "SUB_NAP",
    "indexGlobalInt": 3,
    "tagMuseumNameAltStringList32": "SUB_DMI",
    "tagMuseumNameAltStringList35": "SUB_ITA",
    "tagMuseumNameAltStringList34": "SUB_JUL",
    "nameFullString": "Room Russia",
    "nameAltString": "ROM_RUS",
    "parentNameAltString": "FLR_002",
    "tagMuseumNameAltStringList43": "TVR_TAL",
    "tagMuseumNameAltStringList20": "NOA_DES",
    "fullBoolean": true,
    "tagMuseumNameAltStringList19": "NOA_LIF",
    "tagMuseumNameAltStringList18": "NOA_LOV",
    "tagMuseumNameAltStringList11": "NDV_DES",
    "explanationStringArray3": "Room Russia Explanation 4",
    "tagMuseumNameAltStringList10": "NDV_SLO",
    "tagMuseumNameAltStringList13": "NIV_DIE",
    "tagMuseumNameAltStringList12": "NIV_DIS",
    "tagMuseumNameAltStringList15": "NTV_KIL",
    "tagMuseumNameAltStringList14": "NTV_ASS",
    "explanationStringArray0": "Room Russia Explanation 1",
    "tagMuseumNameAltStringList17": "NOA_NOI",
    "explanationStringArray1": "Room Russia Explanation 2",
    "tagMuseumNameAltStringList16": "NOA_EXH",
    "explanationStringArray2": "Room Russia Explanation 3",
    "tagMuseumNameAltStringList30": "SUB_BOD",
    "tagMuseumNameAltStringList31": "SUB_ROM",
    "typeString": "ROM",
    "tagMuseumNameAltStringList29": "NOU_JOB",
    "tagMuseumNameAltStringList24": "NOU_SID",
    "tagMuseumNameAltStringList23": "NOU_CRO",
    "tagMuseumNameAltStringList22": "NOU_CIG",
    "tagMuseumNameAltStringList21": "NOA_WOR",
    "tagMuseumNameAltStringList28": "NOU_DCR",
    "indexLocalInt": 1,
    "tagMuseumNameAltStringList27": "NOU_FLO",
    "tagMuseumNameAltStringList26": "NOU_STA",
    "tagMuseumNameAltStringList25": "NOU_STO"
  }
]